pyaligner/__init__.py
pyaligner/notebooks/first.ipynb
pyaligner/scripts/aligner.py
pyaligner/scripts/gui.py
pyaligner/utils/__init__.py
pyaligner/utils/utils.py
pyaligner-0.2.0.dist-info/LICENSE
pyaligner-0.2.0.dist-info/METADATA
pyaligner-0.2.0.dist-info/WHEEL
pyaligner-0.2.0.dist-info/entry_points.txt
pyaligner-0.2.0.dist-info/top_level.txt
pyaligner-0.2.0.dist-info/RECORD
